{
	"requestSources": [
		{
			"rbsSource": "ice",
			"rbsChannel": "ice",
			"acrsChannelClass": "Voice",
			"acrsChannelType": "Branded",
			"acrsChannel": "Contact Center",
			"acrsSubChannel": "Contact Center",
			"acrsVendor": "ICECC",
			"channelName": "ice"
		},
		{
			"rbsSource": "mgmri",
			"rbsChannel": "web",
			"acrsChannelClass": "Web",
			"acrsChannelType": "Branded",
			"acrsChannel": "Web",
			"acrsSubChannel": "Web",
			"acrsVendor": "WEBBE",
			"channelName": "mlife"
		},
		{
			"rbsSource": "app",
			"rbsChannel": "mobile",
			"acrsChannelClass": "Web",
			"acrsChannelType": "Branded",
			"acrsChannel": "Web",
			"acrsSubChannel": "Web",
			"acrsVendor": "WEBBE",
			"channelName": "mlife"
		},
		{
			"rbsSource": "66964e2b-2550-4476-84c3-1a4c0c5c067f",
			"rbsChannel": "web",
			"acrsChannelClass": "Web",
			"acrsChannelType": "Branded",
			"acrsChannel": "Web",
			"acrsSubChannel": "MV001",
			"acrsVendor": "WEBBE",
			"channelName": "mgmgrandlv"
		},
		{
			"rbsSource": "dc00e77f-d6bb-4dd7-a8ea-dc33ee9675ad",
			"rbsChannel": "web",
			"acrsChannelClass": "Web",
			"acrsChannelType": "Branded",
			"acrsChannel": "Web",
			"acrsSubChannel": "MV021",
			"acrsVendor": "WEBBE",
			"channelName": "newyorknewyork"
		},
		{
			"rbsSource": "44e610ab-c209-4232-8bb4-51f7b9b13a75",
			"rbsChannel": "web",
			"acrsChannelClass": "Web",
			"acrsChannelType": "Branded",
			"acrsChannel": "Web",
			"acrsSubChannel": "MV190",
			"acrsVendor": "WEBBE",
			"channelName": "bellagio"
		},
		{
			"rbsSource": "e0f70eb3-7e27-4c33-8bcd-f30bf3b1103a",
			"rbsChannel": "web",
			"acrsChannelClass": "Web",
			"acrsChannelType": "Branded",
			"acrsChannel": "Web",
			"acrsSubChannel": "MV275",
			"acrsVendor": "WEBBE",
			"channelName": "mandalaybay"
		},
		{
			"rbsSource": "1f3ed672-3f8f-44d8-9215-81da3c845d83",
			"rbsChannel": "web",
			"acrsChannelClass": "Web",
			"acrsChannelType": "Branded",
			"acrsChannel": "Web",
			"acrsSubChannel": "MV005",
			"acrsVendor": "WEBBE",
			"channelName": "signature"
		},
		{
			"rbsSource": "6c5cff3f-f01a-4f9b-87ab-8395ae8108db",
			"rbsChannel": "web",
			"acrsChannelClass": "Web",
			"acrsChannelType": "Branded",
			"acrsChannel": "Web",
			"acrsSubChannel": "MV938",
			"acrsVendor": "WEBBE",
			"channelName": "vdara"
		},
		{
			"rbsSource": "8bf670c2-3e89-412b-9372-6c87a215e442",
			"rbsChannel": "web",
			"acrsChannelClass": "Web",
			"acrsChannelType": "Branded",
			"acrsChannel": "Web",
			"acrsSubChannel": "MV275",
			"acrsVendor": "WEBBE",
			"channelName": "delano"
		},
		{
			"rbsSource": "607c07e7-3e31-4e4c-a4e1-f55dca66fea2",
			"rbsChannel": "web",
			"acrsChannelClass": "Web",
			"acrsChannelType": "Branded",
			"acrsChannel": "Web",
			"acrsSubChannel": "MV280",
			"acrsVendor": "WEBBE",
			"channelName": "luxor"
		},
		{
			"rbsSource": "f8d6a944-7816-412f-a39a-9a63aad26833",
			"rbsChannel": "web",
			"acrsChannelClass": "Web",
			"acrsChannelType": "Branded",
			"acrsChannel": "Web",
			"acrsSubChannel": "MV285",
			"acrsVendor": "WEBBE",
			"channelName": "excalibur"
		},
		{
			"rbsSource": "2159252c-60d3-47db-bbae-b1db6bb15072",
			"rbsChannel": "web",
			"acrsChannelClass": "Web",
			"acrsChannelType": "Branded",
			"acrsChannel": "Web",
			"acrsSubChannel": "MV290",
			"acrsVendor": "WEBBE",
			"channelName": "montecarlo"
		},
		{
			"rbsSource": "e2704b04-d515-45b0-8afd-4fa1424ff0a8",
			"rbsChannel": "web",
			"acrsChannelClass": "Web",
			"acrsChannelType": "Branded",
			"acrsChannel": "Web",
			"acrsSubChannel": "MV930",
			"acrsVendor": "WEBBE",
			"channelName": "aria"
		},
		{
			"rbsSource": "0990fdce-7fc8-41b1-b8b6-9a25dce3db55",
			"rbsChannel": "web",
			"acrsChannelClass": "Web",
			"acrsChannelType": "Branded",
			"acrsChannel": "Web",
			"acrsSubChannel": "MV307",
			"acrsVendor": "WEBBE",
			"channelName": "mgmnationalharbor"
		},
		{
			"rbsSource": "4a65a92a-962b-433e-841c-37e18dc5d68d",
			"rbsChannel": "web",
			"acrsChannelClass": "Web",
			"acrsChannelType": "Branded",
			"acrsChannel": "Web",
			"acrsSubChannel": "MV016",
			"acrsVendor": "WEBBE",
			"channelName": "mgmgranddetroit"
		},	
		{
			"rbsSource": "13b178b0-8beb-43d5-af25-1738b7267e63",
			"rbsChannel": "web",
			"acrsChannelClass": "Web",
			"acrsChannelType": "Branded",
			"acrsChannel": "Web",
			"acrsSubChannel": "MV180",
			"acrsVendor": "WEBBE",
			"channelName": "beaurivage"
		},	
		{
			"rbsSource": "bee81f88-286d-43dd-91b5-3917d9d62a68",
			"rbsChannel": "web",
			"acrsChannelClass": "Web",
			"acrsChannelType": "Branded",
			"acrsChannel": "Web",
			"acrsSubChannel": "MV290",
			"acrsVendor": "WEBBE",
			"channelName": "parkmgm"
		},
		{
			"rbsSource": "40b61feb-750a-45df-ae68-e23e6272b16b",
			"rbsChannel": "web",
			"acrsChannelClass": "Web",
			"acrsChannelType": "Branded",
			"acrsChannel": "Web",
			"acrsSubChannel": "MV306",
			"acrsVendor": "WEBBE",
			"channelName": "mgmspringfield"
		},
		{
			"rbsSource": "773000cc-468a-4d86-a38f-7ae78ecfa6aa",
			"rbsChannel": "web",
			"acrsChannelClass": "Web",
			"acrsChannelType": "Branded",
			"acrsChannel": "Web",
			"acrsSubChannel": "MV304",
			"acrsVendor": "WEBBE",
			"channelName": "borgata"
		},
		{
			"rbsSource": "movableink",
			"rbsChannel": "third-party",
			"acrsChannelClass": "Web",
			"acrsChannelType": "Branded",
			"acrsChannel": "Web",
			"acrsSubChannel": "Web",
			"acrsVendor": "WEBBE",
			"channelName": "mlife"
		},
		{
			"rbsSource": "ota-insights",
			"rbsChannel": "third-party",
			"acrsChannelClass": "Web",
			"acrsChannelType": "Branded",
			"acrsChannel": "Web",
			"acrsSubChannel": "Web",
			"acrsVendor": "WEBBE",
			"channelName": "mlife"
		},
		{
			"rbsSource": "e5d3f1c9-833a-83f1-e053-d303fe0ad83c",
			"rbsChannel": "web",
			"acrsChannelClass": "Web",
			"acrsChannelType": "Branded",
			"acrsChannel": "Web",
			"acrsSubChannel": "Web",
			"acrsVendor": "WEBBE",
			"channelName": "mlife"
		}	
	]
}
